wayback_mcp/__init__.py
wayback_mcp/server.py
wayback_mcp-0.1.2.dist-info/licenses/LICENSE
wayback_mcp-0.1.2.dist-info/METADATA
wayback_mcp-0.1.2.dist-info/WHEEL
wayback_mcp-0.1.2.dist-info/entry_points.txt
wayback_mcp-0.1.2.dist-info/top_level.txt
wayback_mcp-0.1.2.dist-info/RECORD
