Metadata-Version: 2.4
Name: wayback-mcp
Version: 0.1.2
Summary: Wayback Machine MCP server (Python)
Author: sisilet
License: MIT License
Project-URL: Homepage, https://github.com/sisilet/wayback_mcp
Project-URL: Repository, https://github.com/sisilet/wayback_mcp
Project-URL: Issues, https://github.com/sisilet/wayback_mcp/issues
Keywords: mcp,model-context-protocol,wayback,archive.org,internet-archive
Classifier: License :: OSI Approved :: MIT License
Classifier: Programming Language :: Python :: 3
Classifier: Programming Language :: Python :: 3 :: Only
Classifier: Programming Language :: Python :: 3.10
Classifier: Programming Language :: Python :: 3.11
Classifier: Programming Language :: Python :: 3.12
Classifier: Intended Audience :: Developers
Classifier: Topic :: Internet :: WWW/HTTP
Classifier: Topic :: Software Development :: Libraries
Classifier: Environment :: Console
Requires-Python: >=3.10
License-File: LICENSE
Requires-Dist: mcp>=1.0.0
Requires-Dist: httpx>=0.27.0
Requires-Dist: pydantic>=2.7.0
Dynamic: license-file
